lib_preproc/__init__.py
lib_preproc/preprocessing.py
lib_preprocessing_REMLA23_team2-0.1.21.dist-info/METADATA
lib_preprocessing_REMLA23_team2-0.1.21.dist-info/WHEEL
lib_preprocessing_REMLA23_team2-0.1.21.dist-info/top_level.txt
lib_preprocessing_REMLA23_team2-0.1.21.dist-info/RECORD
