Metadata-Version: 2.1
Name: lib-preprocessing-REMLA23-team2
Version: 0.1.21
Summary: Library for preprocessing the data
Author: remla23_team2
License: MIT
